<xml src="kx02-07.xml">
<juan n="02-07">午集</juan>
<part>玉部</part>
<wh n="kby0000" unicode="248F8" wid="047">𤣸</wh>
<sc n="7"/>
<ps n="玉部3畫"/>
<zy>注音：ㄅㄚ-</zy>
<t>
<ph/>《奚韻》：音八──玉也。
</t>
<wh n="kby0000" unicode="3EB4" wid="048">㺴</wh>
<sc n="8"/>
<ps n="玉部4畫"/>
<zy>注音：ㄅㄚ-</zy>
<t>
<ph/>《五音篇海》：補戛切──神名。
</t>
<wh n="kby0000" unicode="3EB5" wid="049">㺵</wh>
<sc n="8"/>
<ps n="玉部4畫"/>
<zy>注音：ㄐㄧㄡˇ</zy>
<t>
<ph/>《川篇》：音久──黑玉貌。
</t>
<wh n="kby0000" unicode="2490D" wid="050">𤤍</wh>
<sc n="8"/>
<ps n="玉部4畫"/>
<t>
<ph/>《字彙補》：與瑉同。《周禮．弁師註》：𤤍，惡玉名。
</t>
<wh n="kby0000" unicode="24931" wid="051">𤤱</wh>
<sc n="9"/>
<ps n="玉部5畫"/>
<zy>注音：ㄒㄧˇ</zy>
<t>
<ph/>《川篇》：音徙──玉印。
</t>
<wh n="kby0000" unicode="24932" wid="052">𤤲</wh>
<sc n="9"/>
<ps n="玉部5畫"/>
<zy>注音：ㄎㄨㄥˇ</zy>
<t>
<ph/>《川篇》：音孔──玉也。
</t>
<wh n="kby0000" unicode="3EC3" wid="053">㻃</wh>
<sc n="10"/>
<ps n="玉部6畫"/>
<zy>注音：ㄑㄩˇ</zy>
<t>
<ph/>《篇海類編》：音曲──骫曲也。又，玉也。
</t>
<wh n="kby0000" unicode="24977" wid="054">𤥷</wh>
<sc n="11"/>
<ps n="玉部7畫"/>
<zy>注音：ㄑㄩㄢˊ,ㄒㄩㄢˊ</zy>
<t>
<ph/>《龍龕》：音全──石似玉也。又，音旋。
</t>
<wh n="kby0000" unicode="249AE" wid="055">𤦮</wh>
<sc n="12"/>
<ps n="玉部8畫"/>
<zy>注音：ㄓˋ</zy>
<t>
<ph/>《篇海類編》：直意切，音治──玉也
</t>
<wh n="kby0000" unicode="249E0" wid="056">𤧠</wh>
<sc n="13"/>
<ps n="玉部9畫"/>
<zy>注音：ㄖㄨㄢˇ</zy>
<t>
<ph/>《五音篇海》：音阮──光也。
</t>
<wh n="kby0000" unicode="24A3B" wid="057">𤨻</wh>
<sc n="15"/>
<ps n="玉部11畫"/>
<zy>注音：ㄌㄧㄥˋ</zy>
<t>
<ph/>《五音篇海》：音令──以玉事人。
</t>
<wh n="kby0000" unicode="24A68" wid="058">𤩨</wh>
<sc n="16"/>
<ps n="玉部12畫"/>
<zy>注音：ㄏㄢˋ</zy>
<t>
<ph/>《字彙補》：戸散切，音旱──玉色也。
</t>
<wh n="kby0000" unicode="24A69" wid="059">𤩩</wh>
<sc n="16"/>
<ps n="玉部12畫"/>
<zy>注音：ㄏㄠˋ</zy>
<t>
<ph/>《川篇》：音号──玉也。
</t>
<wh n="kby0000" unicode="74B3" wid="060">璳</wh>
<sc n="17"/>
<ps n="玉部13畫"/>
<zy>注音：ㄊㄧㄢˊ</zy>
<t>
<ph/>《篇海類編》：音田──玉光。
</t>
<wh n="kby0000" unicode="24AD8" wid="061">𤫘</wh>
<sc n="22"/>
<ps n="玉部19畫"/>
<zy>注音：ㄋㄠˊ</zy>
<t>
<ph/>《五音篇海》：奴刀切──玉名。
</t>
<part>瓜部</part>
<pb id="1489"/>
<wh n="kby0000" unicode="24B0C" wid="001">𤬌</wh>
<sc n="14"/>
<ps n="瓜部9畫"/>
<zy>注音：ㄩㄢˊ</zy>
<t>
<ph/>《川篇》：音緣──瓜𤬌。
</t>
<wh n="kby0000" unicode="24B21" wid="002">𤬡</wh>
<sc n="23"/>
<ps n="瓜部18畫"/>
<t>
<ph/>《字彙補》：瓢本字。
</t>
<part>瓦部</part>
<wh n="kby0000" unicode="24B3D" wid="003">𤬽</wh>
<sc n="10"/>
<ps n="瓦部5畫"/>
<t>
<ph/>《字彙補》：古湯切，音岡──大甕。
</t>
<wh n="kby0000" unicode="24B4B" wid="004">𤭋</wh>
<sc n="11"/>
<ps n="瓦部6畫"/>
<zy>注音：ㄨㄥ-</zy>
<t>
<ph/>《龍龕》：古獲切──瓦器也。又，烏耕切──義同。
</t>
<wh n="kby0000" unicode="24B96" wid="005">𤮖</wh>
<sc n="13"/>
<ps n="瓦部10畫"/>
<t>
<ph/>《篇海類編》：古獲切，音國──瓦器。
</t>
<wh n="kby0000" unicode="24B74" wid="006">𤭴</wh>
<sc n="14"/>
<ps n="瓦部9畫"/>
<zy>注音：ㄙㄨˋ</zy>
<t>
<ph/>《字彙補》：心卜切，音宿──不能行也。
</t>
<wh n="kby0000" unicode="24B95" wid="007">𤮕</wh>
<sc n="17"/>
<ps n="瓦部11畫"/>
<t>
<ph/>《字彙補》：音未詳。《武林舊事》：大度金𤮕。
</t>
<wh n="kby0000" unicode="24BAF" wid="008">𤮯</wh>
<sc n="22"/>
<ps n="瓦部17畫"/>
<zy>注音：ㄒㄧㄝˊ</zy>
<t>
<ph/>《五音集韻》：音攜──宇下空也。
</t>
<part>生部</part>
<wh n="kby0000" unicode="24BD6" wid="009">𤯖</wh>
<sc n="8"/>
<ps n="生部3畫"/>
<zy>注音：ㄙㄨㄟ-</zy>
<t>
<ph/>《五音篇韻》：心追切，音雖──不正也。
</t>
<wh n="kby0000" unicode="7527" wid="010">甧</wh>
<sc n="14"/>
<ps n="生部9畫"/>
<zy>注音：ㄙㄣ-</zy>
<t>
<ph/>《字彙補》：所音切，音森──衆也。
</t>
<part>用部</part>
<wh n="kby0000" unicode="24C11" wid="011">𤰑</wh>
<sc n="23"/>
<ps n="用部18畫"/>
<zy>注音：ㄆㄨˊ</zy>
<t>
<ph/>《字彙補》：皮夫切，音蒲──𤰑𡳴，螟蛉也。
</t>
<part>田部</part>
<wh n="kby0000" unicode="3F5A" wid="012">㽚</wh>
<sc n="9"/>
<ps n="田部4畫"/>
<zy>注音：ㄔˇ</zy>
<t>
<ph/>《篇海類編》：昌石切，音尺──田器。又，地名。
</t>
<wh n="kby0000" unicode="24C4B" wid="013">𤱋</wh>
<sc n="9"/>
<ps n="田部4畫"/>
<zy>注音：ㄖㄢˊ</zy>
<t>
<ph/>《字彙補》：汝鹽切，音髥──巨龜。
</t>
<wh n="kby0000" unicode="24C63" wid="014">𤱣</wh>
<sc n="10"/>
<ps n="田部5畫"/>
<zy>注音：ㄋㄢˊ</zy>
<t>
<ph/>《字彙補》：那含切，音南──龜有甲。
</t>
<wh n="kby0000" unicode="24C7A" wid="015">𤱺</wh>
<sc n="11"/>
<ps n="田部6畫"/>
<t>
<ph/>《字彙補》：古位切，音檜──𤱺𡏛。
</t>
<wh n="kby0000" unicode="24C8D" wid="016">𤲍</wh>
<sc n="12"/>
<ps n="田部7畫"/>
<zy>注音：ㄒㄧㄚˊ</zy>
<t>
<ph/>《字彙補》：下甲切，音轄──相著也。
</t>
<wh n="kby0000" unicode="24CB8" wid="017">𤲸</wh>
<sc n="15"/>
<ps n="田部10畫"/>
<zy>注音：ㄗ-</zy>
<t>
<ph/>《五音篇海》：音茲──《魯郊禮》𤲸。又，益也。
</t>
<wh n="kby0000" unicode="24CC5" wid="018">𤳅</wh>
<sc n="15"/>
<ps n="田部10畫"/>
<zy>注音：ㄔㄚˋ</zy>
<t>
<ph/>《字彙補》：初瓦切，瘥上聲──幕宇甲聲也。又，雪中行。
</t>
<wh n="kby0000" unicode="24CDF" wid="019">𤳟</wh>
<sc n="17"/>
<ps n="田部12畫"/>
<zy>注音：ㄖㄨㄢˊ</zy>
<t>
<ph/>《字彙補》：而宣切，音𤲬──城下田也。
</t>
<wh n="kby0000" unicode="24CE0" wid="020">𤳠</wh>
<sc n="17"/>
<ps n="田部12畫"/>
<zy>注音：ㄔㄡˊ</zy>
<t>
<ph/>《川篇》：音紬──田也。
</t>
<wh n="kby0000" unicode="24D0E" wid="021">𤴎</wh>
<sc n="28"/>
<ps n="田部22畫"/>
<t>
<ph/>《字彙補》：疃字。見《石鼓文》。《字彙》作𤳿，誤。
</t>
<part>疒部</part>
<wh n="kby0000" unicode="24D25" wid="022">𤴥</wh>
<sc n="6"/>
<ps n="疒部1畫"/>
<zy>注音：ㄐㄧㄡ-</zy>
<t>
<ph/>《川篇》：音鳩──病也。
</t>
<wh n="kby0000" unicode="24D2E" wid="023">𤴮</wh>
<sc n="7"/>
<ps n="疒部2畫"/>
<zy>注音：ㄐㄧㄡ-</zy>
<t>
<ph/>《龍龕》：居幽切──腹急病也。
</t>
<wh n="kby0000" unicode="24D75" wid="024">𤵵</wh>
<sc n="10"/>
<ps n="疒部5畫"/>
<zy>注音：ㄩˇ</zy>
<t>
<ph/>《龍龕》：以主切──病也、憂心也。
</t>
<wh n="kby0000" unicode="24D93" wid="025">𤶓</wh>
<sc n="11"/>
<ps n="疒部6畫"/>
<zy>注音：ㄓˇ</zy>
<t>
<ph/>《篇海類編》：音旨──小疾。
</t>
<wh n="kby0000" unicode="24D94" wid="026">𤶔</wh>
<sc n="11"/>
<ps n="疒部6畫"/>
<zy>注音：ㄐㄧㄡˋ</zy>
<t>
<ph/>《龍龕》：音救──病也。
</t>
<wh n="kby0000" unicode="24DC0" wid="027">𤷀</wh>
<sc n="12"/>
<ps n="疒部7畫"/>
<zy>注音：ㄨㄤ-</zy>
<t>
<ph/>《搜眞玉鏡》：烏光切，音汪──瘦也。
</t>
<wh n="kby0000" unicode="24DC1" wid="028">𤷁</wh>
<sc n="12"/>
<ps n="疒部7畫"/>
<zy>注音：ㄆㄟˊ</zy>
<t>
<ph/>《五音篇海》：補回切──結痛也。
</t>
<wh n="kby0000" unicode="24DF9" wid="029">𤷹</wh>
<sc n="13"/>
<ps n="疒部7畫"/>
<zy>注音：ㄏㄨㄟˋ</zy>
<t>
<ph/>《篇海《類編》：烏外切──潔病也。
</t>
<wh n="kby0000" unicode="24DF7" wid="030">𤷷</wh>
<sc n="13"/>
<ps n="疒部8畫"/>
<zy>注音：ㄜˋ</zy>
<t>
<ph/>《龍龕》：烏合切──短氣也。
</t>
<wh n="kby0000" unicode="24DF8" wid="031">𤷸</wh>
<sc n="13"/>
<ps n="疒部8畫"/>
<zy>注音：ㄧㄚˇ</zy>
<t>
<ph/>《龍龕》：烏雅切──不言也。
</t>
<wh n="kby0000" unicode="24E29" wid="032">𤸩</wh>
<sc n="14"/>
<ps n="疒部10畫"/>
<zy>注音：ㄋㄡˊ</zy>
<t>
<ph/>《龍龕》：奴侯切──兔子也。
</t>
<wh n="kby0000" unicode="24E5C" wid="033">𤹜</wh>
<sc n="15"/>
<ps n="疒部10畫"/>
<zy>注音：ㄧㄥˊ</zy>
<t>
<ph/>《篇海類編》：音營──病也。
</t>
<wh n="kby0000" unicode="24E5B" wid="034">𤹛</wh>
<sc n="15"/>
<ps n="疒部10畫"/>
<zy>注音：ㄔㄣˊ</zy>
<t>
<ph/>《五音篇海》：音沉──腹病也。
</t>
<wh n="kby0000" unicode="24E80" wid="035">𤺀</wh>
<sc n="16"/>
<ps n="疒部11畫"/>
<zy>注音：ㄕㄨㄞ-</zy>
<t>
<ph/>《龍龕》：所追切──病也。
</t>
<wh n="kby0000" unicode="764B" wid="036">癋</wh>
<sc n="17"/>
<ps n="疒部12畫"/>
<zy>注音：ㄏㄜˋ</zy>
<t>
<ph/>《字彙補》：何各切，音鶴──心病。
</t>
<wh n="kby0000" unicode="24EB7" wid="037">𤺷</wh>
<sc n="17"/>
<ps n="疒部12畫"/>
<zy>注音：ㄐㄧˊ</zy>
<t>
<ph/>《篇海類編》：音極──病也。
</t>
<wh n="kby0000" unicode="24EB8" wid="038">𤺸</wh>
<sc n="17"/>
<ps n="疒部12畫"/>
<zy>注音：ㄨㄟˋ</zy>
<t>
<ph/>《龍龕》：烏對切──𤺸𡯵也。
</t>
<wh n="kby0000" unicode="24EEE" wid="039">𤻮</wh>
<sc n="19"/>
<ps n="疒部14畫"/>
<t>
<ph/>《字彙補》：應本字。
</t>
<wh n="kby0000" unicode="24F17" wid="040">𤼗</wh>
<sc n="23"/>
<ps n="疒部18畫"/>
<zy>注音：ㄐㄩㄝˊ</zy>
<t>
<ph/>《川篇》：居月切──倒病也。
</t>
<part>癶部</part>
<wh n="kby0000" unicode="24F33" wid="041">𤼳</wh>
<sc n="13"/>
<ps n="癶部8畫"/>
<zy>注音：ㄐㄩˇ</zy>
<t>
<ph/>《龍龕》：九六切──兩手𤼳。
</t>
<part>白部</part>
<wh n="kby0000" unicode="24F41" wid="042">𤽁</wh>
<sc n="7"/>
<ps n="白部2畫"/>
<zy>注音：ㄓ-</zy>
<t>
<ph/>《海篇》：音支──白也。
</t>
<wh n="kby0000" unicode="24F46" wid="043">𤽆</wh>
<sc n="8"/>
<ps n="白部3畫"/>
<zy>注音：ㄓ-</zy>
<t>
<ph/>《五音篇海》：音支──白也。
</t>
<wh n="kby0000" unicode="24F47" wid="044">𤽇</wh>
<sc n="8"/>
<ps n="白部3畫"/>
<zy>注音：ㄑㄩㄢˊ</zy>
<t>
<ph/>《篇海類編》：音全──水泉。
</t>
<wh n="kby0000" unicode="24F56" wid="045">𤽖</wh>
<sc n="9"/>
<ps n="白部4畫"/>
<zy>注音：ㄇㄧㄡˊ</zy>
<t>
<ph/>《集韻》：亡幽切，繆平聲──細也。
</t>
<wh n="kby0000" unicode="24FA6" wid="046">𤾦</wh>
<sc n="17"/>
<ps n="白部12畫"/>
<zy>注音：ㄔㄡˊ</zy>
<t>
<ph/>《海篇》：音讎──詞也。
</t>
<wh n="kby0000" unicode="24FB2" wid="047">𤾲</wh>
<sc n="19"/>
<ps n="白部14畫"/>
<zy>注音：ㄌㄧㄢˊ</zy>
<t>
<ph/>《五音篇海》：音廉──白光。
</t>
<wh n="kby0000" unicode="24FB6" wid="048">𤾶</wh>
<sc n="20"/>
<ps n="白部15畫"/>
<t>
<ph/>《餘文》：俗𤿀字。
</t>
<wh n="kby0000" unicode="24FC3" wid="049">𤿃</wh>
<sc n="24"/>
<ps n="白部19畫"/>
<zy>注音：ㄐㄩㄝˊ</zy>
<t>
<ph/>《字彙補》：字爵切，音嚼。《廣雅》：皭皭景景，白也。
</t>
<pb id="1490"/>
<part>皮部</part>
<wh n="kby0000" unicode="2501E" wid="001">𥀞</wh>
<sc n="16"/>
<ps n="皮部11畫"/>
<zy>注音：ㄔㄨㄟˋ</zy>
<t>
<ph/>《龍龕》：楚貴切──粟體也。
</t>
<part>皿部</part>
<wh n="kby0000" unicode="76C1" wid="002">盁</wh>
<sc n="7"/>
<ps n="皿部2畫"/>
<t>
<ph/>《字彙補》：漢靈臺𥓓盈字。
</t>
<wh n="kby0000" unicode="2505B" wid="003">𥁛</wh>
<sc n="10"/>
<ps n="皿部5畫"/>
<zy>注音：ㄓㄠ-</zy>
<t>
<ph/>《龍龕》：音昭──器也。
</t>
<wh n="kby0000" unicode="2505C" wid="004">𥁜</wh>
<sc n="10"/>
<ps n="皿部5畫"/>
<zy>注音：ㄓㄠ-</zy>
<t>
<ph/>《說文長箋》：止遙切，音招──器名也。《博古圖》有𥁜盉鐘銘，《字彙》作盄。
</t>
<wh n="kby0000" unicode="2506A" wid="005">𥁪</wh>
<sc n="11"/>
<ps n="皿部6畫"/>
<t>
<ph/>《字彙補》：與孟同。見〈韓敕修孔子廟後碑〉。
</t>
<wh n="kby0000" unicode="25076" wid="006">𥁶</wh>
<sc n="12"/>
<ps n="皿部7畫"/>
<t>
<ph/>《字彙補》：與饛同。見楊愼《奇字韻》。
</t>
<wh n="kby0000" unicode="250B5" wid="007">𥂵</wh>
<sc n="17"/>
<ps n="皿部12畫"/>
<zy>注音：ㄐㄧㄣ-</zy>
<t>
<ph/>《五音集韻》：將鄰切，音津──氣之液也。
</t>
<wh n="kby0000" unicode="250BE" wid="008">𥂾</wh>
<sc n="18"/>
<ps n="皿部13畫"/>
<zy>注音：ㄙㄨㄛˇ</zy>
<t>
<ph/>《篇海類編》：始土切，音所──載器也。
</t>
<wh n="kby0000" unicode="250CD" wid="009">𥃍</wh>
<sc n="20"/>
<ps n="皿部15畫"/>
<t>
<ph/>《說文長箋》：與盭同。
</t>
<wh n="kby0000" unicode="250D0" wid="010">𥃐</wh>
<sc n="20"/>
<ps n="皿部15畫"/>
<zy>注音：ㄔㄚ-</zy>
<t>
<ph/>《廣韻》：丑㘝切，音踔──五味調肉菜。
</t>
<part>目部</part>
<wh n="kby0000" unicode="401E" wid="011">䀞</wh>
<sc n="9"/>
<ps n="目部4畫"/>
<zy>注音：ㄊㄠ-</zy>
<t>
<ph/>《字彙補》：湯勞切，音叨──目重瞼也。見𠌪字註。
</t>
<wh n="kby0000" unicode="25158" wid="012">𥅘</wh>
<sc n="10"/>
<ps n="目部5畫"/>
<zy>注音：ㄓㄣˇ</zy>
<t>
<ph/>《龍龕》：之忍切──明也。
</t>
<wh n="kby0000" unicode="25159" wid="013">𥅙</wh>
<sc n="10"/>
<ps n="目部5畫"/>
<zy>注音：ㄅㄧㄥˇ</zy>
<t>
<ph/>《篇海類編》：音丙──明也。
</t>
<wh n="kby0000" unicode="25185" wid="014">𥆅</wh>
<sc n="11"/>
<ps n="目部5畫"/>
<zy>注音：ㄐㄧㄤ-</zy>
<t>
<ph/>《篇海類編》：音丙──明也。
</t>
<wh n="kby0000" unicode="2032A" wid="015">𠌪</wh>
<sc n="11"/>
<ps n="目部6畫"/>
<zy>注音：ㄊㄠ-</zy>
<t>
<ph/>《篇海類編》：他刀切，音滔──目通白。《楊氏古音》：唐小說，術士相裴夫人，目𠌪而緩，主淫。俗誤作脩長之脩，非。又作䀞。
</t>
<wh n="kby0000" unicode="25186" wid="016">𥆆</wh>
<sc n="11"/>
<ps n="目部6畫"/>
<t>
<ph/>《轉注古音》：𥆆與貿同，王柏云，貿相易也，而爲𥆆矇之貿。《素問》：目𥆆𥆆然。
</t>
<wh n="kby0000" unicode="25187" wid="017">𥆇</wh>
<sc n="11"/>
<ps n="目部6畫"/>
<zy>注音：ㄔㄨㄤˋ</zy>
<t>
<ph/>《篇海類編》：丑絳切，音創──與𥈄同，直視也。
</t>
<wh n="kby0000" unicode="251C3" wid="018">𥇃</wh>
<sc n="12"/>
<ps n="目部7畫"/>
<zy>注音：ㄖㄢˊ</zy>
<t>
<ph/>《餘文》：如延切──犬肉也。
</t>
<wh n="kby0000" unicode="251C4" wid="019">𥇄</wh>
<sc n="12"/>
<ps n="目部7畫"/>
<zy>注音：ㄋㄧˋ,ㄨㄛˋ</zy>
<t>
<ph/>《篇海類編》：女利切，音膩──目深貌。又，烏活切，音斡──義同。
</t>
<wh n="kby0000" unicode="25188" wid="020">𥆈</wh>
<sc n="11"/>
<ps n="目部6畫"/>
<zy>注音：ㄏㄨㄤ-,ㄇㄤˊ</zy>
<t>
<ph/>《龍龕》：音荒──目不明也。又，狼𥆈也。又，音忙──義同。
</t>
<wh n="kby0000" unicode="251C7" wid="021">𥇇</wh>
<sc n="12"/>
<ps n="目部7畫"/>
<zy>注音：ㄙㄨㄛ-</zy>
<t>
<ph/>《篇海類編》：先何切，音梭──偷見貌。
</t>
<wh n="kby0000" unicode="403F" wid="022">䀿</wh>
<sc n="12"/>
<ps n="目部7畫"/>
<zy>注音：ㄔˋ</zy>
<t>
<ph/>《字彙補》：昌志切，音熾──瞥也。
</t>
<wh n="kby0000" unicode="251FE" wid="023">𥇾</wh>
<sc n="13"/>
<ps n="目部8畫"/>
<zy>注音：ㄐㄧㄝ-</zy>
<t>
<ph/>《龍龕》：卽葉切，音接──目𥇾也。
</t>
<wh n="kby0000" unicode="23AAD" wid="024">𣪭</wh>
<sc n="13"/>
<ps n="目部8畫"/>
<zy>注音：ㄅㄧㄢˋ</zy>
<t>
<ph/>《字彙補》：邦見切，音遍──視也。
</t>
<wh n="kby0000" unicode="251C5" wid="025">𥇅</wh>
<sc n="13"/>
<ps n="目部8畫"/>
<zy>注音：ㄇㄢˇ</zy>
<t>
<ph/>《篇海類編》：母版切，蠻上聲──與睌同。𥇅䁂，目視貌。
</t>
<wh n="kby0000" unicode="25189" wid="026">𥆉</wh>
<sc n="11"/>
<ps n="目部6畫"/>
<zy>注音：ㄩˋ</zy>
<t>
<ph/>《川篇》：音&kxr-01685;──視也。
</t>
<wh n="kby0000" unicode="251C6" wid="027">𥇆</wh>
<sc n="12"/>
<ps n="目部8畫"/>
<zy>注音：ㄇㄧˊ</zy>
<t>
<ph/>《川篇》：音彌──眇目曰𥇆。
</t>
<wh n="kby0000" unicode="251FF" wid="028">𥇿</wh>
<sc n="13"/>
<ps n="目部8畫"/>
<zy>注音：ㄒㄩˋ</zy>
<t>
<ph/>《篇海類編》：呼狊切，音旭──視𥇿。
</t>
<wh n="kby0000" unicode="22FA5" wid="029">𢾥</wh>
<sc n="13"/>
<ps n="目部8畫"/>
<t>
<ph/>《說文》：䁈本字，視也。
</t>
<wh n="kby0000" unicode="25200" wid="030">𥈀</wh>
<sc n="13"/>
<ps n="目部8畫"/>
<zy>注音：ㄐㄩˋ</zy>
<t>
<ph/>《龍龕》：音俱──左右視貌。
</t>
<wh n="kby0000" unicode="25237" wid="031">𥈷</wh>
<sc n="14"/>
<ps n="目部9畫"/>
<zy>注音：ㄎㄨ-</zy>
<t>
<ph/>《奚韻》：苦骨切，音窟──目袞𥈷。
</t>
<wh n="kby0000" unicode="25238" wid="032">𥈸</wh>
<sc n="14"/>
<ps n="目部9畫"/>
<t>
<ph/>《篇海類編》：居爲切，音歸。《廣雅》：𦥛也。
</t>
<wh n="kby0000" unicode="2523B" wid="033">𥈻</wh>
<sc n="14"/>
<ps n="目部9畫"/>
<zy>注音：ㄧˊ</zy>
<t>
<ph/>《字彙補》：何其切，音移──人姓。
</t>
<wh n="kby0000" unicode="25270" wid="034">𥉰</wh>
<sc n="15"/>
<ps n="目部10畫"/>
<zy>注音：ㄑㄧㄚˋ,ㄏㄢˋ</zy>
<t>
<ph/>《餘文》：苦洽切──陷也。通作䁍。又，胡紺切──目深貌。
</t>
<wh n="kby0000" unicode="252A7" wid="035">𥊧</wh>
<sc n="16"/>
<ps n="目部11畫"/>
<zy>注音：ㄎㄡˋ</zy>
<t>
<ph/>《奚韻》：苦搆切──𥊧瞀，無暇也。
</t>
<wh n="kby0000" unicode="252A8" wid="036">𥊨</wh>
<sc n="16"/>
<ps n="目部11畫"/>
<zy>注音：ㄌㄧˋ</zy>
<t>
<ph/>《餘文》：力智切──竊視也。又，力計切──義同。
</t>
<part>矛部</part>
<wh n="kby0000" unicode="25328" wid="037">𥌨</wh>
<sc n="20"/>
<ps n="目部15畫"/>
<zy>注音：ㄒㄧㄝ-</zy>
<t>
<ph/>《龍龕》：火結切──目不明。
</t>
<wh n="kby0000" unicode="25329" wid="038">𥌩</wh>
<sc n="20"/>
<ps n="目部15畫"/>
<zy>注音：ㄊㄜˋ</zy>
<t>
<ph/>《篇海類編》：他則切，音忒──𥌩䁿，欲臥貌。
</t>
<part>矛部</part>
<wh n="kby0000" unicode="25375" wid="039">𥍵</wh>
<sc n="13"/>
<ps n="矛部8畫"/>
<zy>注音：ㄑㄧㄣˊ</zy>
<t>
<ph/>《五音篇海》：巨巾切──矛柄。
</t>
<wh n="kby0000" unicode="25389" wid="040">𥎉</wh>
<sc n="15"/>
<ps n="矛部10畫"/>
<zy>注音：ㄇㄠˋ,ㄇㄨˊ</zy>
<t>
<ph/>《龍龕》：莫角切──目不明也。又，莫候切──瞽𥎉也。又，莫胡切──𥎉，榆子醬也。
</t>
<wh n="kby0000" unicode="25392" wid="041">𥎒</wh>
<sc n="17"/>
<ps n="矛部12畫"/>
<zy>注音：ㄔㄨㄤ-</zy>
<t>
<ph/>《川篇》：音窓──矛也。
</t>
<part>矢部</part>
<wh n="kby0000" unicode="253B8" wid="042">𥎸</wh>
<sc n="10"/>
<ps n="矢部5畫"/>
<zy>注音：ㄑㄧㄚˋ</zy>
<t>
<ph/>《川篇》：去法切──矢也。
</t>
<wh n="kby0000" unicode="253EF" wid="043">𥏯</wh>
<sc n="14"/>
<ps n="矢部9畫"/>
<zy>注音：ㄓㄞ-</zy>
<t>
<ph/>《川篇》：智宅切，音摘──得水也。
</t>
<wh n="kby0000" unicode="253F0" wid="044">𥏰</wh>
<sc n="14"/>
<ps n="矢部9畫"/>
<zy>注音：ㄓˋ</zy>
<t>
<ph/>《字彙補》：音滯──姓也。
</t>
<part>石部</part>
<pb id="1491"/>
<wh n="kby0000" unicode="25444" wid="001">𥑄</wh>
<sc n="9"/>
<ps n="石部4畫"/>
<zy>注音：ㄑㄧㄚˋ</zy>
<t>
<ph/>《龍龕》：苦八切──石狀也。
</t>
<wh n="kby0000" unicode="25445" wid="002">𥑅</wh>
<sc n="9"/>
<ps n="石部4畫"/>
<zy>注音：ㄎㄥ-</zy>
<t>
<ph/>《川篇》：音坈──破石。
</t>
<wh n="kby0000" unicode="2546F" wid="003">𥑯</wh>
<sc n="10"/>
<ps n="石部5畫"/>
<zy>注音：ㄉㄨˊ</zy>
<t>
<ph/>《字彙補》：徒木切，音獨──種田具。
</t>
<wh n="kby0000" unicode="25470" wid="004">𥑰</wh>
<sc n="10"/>
<ps n="石部5畫"/>
<t>
<ph/>《龍龕》：古壞切，音怪──石似玉也。
</t>
<wh n="kby0000" unicode="25471" wid="005">𥑱</wh>
<sc n="10"/>
<ps n="石部5畫"/>
<zy>注音：ㄑㄧㄝ-</zy>
<t>
<ph/>《篇海類編》：音切──石也。
</t>
<wh n="kby0000" unicode="25472" wid="006">𥑲</wh>
<sc n="10"/>
<ps n="石部5畫"/>
<t>
<ph/>《字彙補》：漢武梁𥓓墠字。
</t>
<wh n="kby0000" unicode="254A7" wid="007">𥒧</wh>
<sc n="11"/>
<ps n="石部6畫"/>
<zy>注音：ㄧㄚˋ</zy>
<t>
<ph/>《川篇》：音訝──石光也。
</t>
<wh n="kby0000" unicode="254A8" wid="008">𥒨</wh>
<sc n="11"/>
<ps n="石部6畫"/>
<zy>注音：ㄌㄨˋ</zy>
<t>
<ph/>《字彙補》：力谷切，音祿──難致貌。揚子《太𤣥經》：拔石𥒨𥒨，力沒以盡。
</t>
<wh n="kby0000" unicode="254A9" wid="009">𥒩</wh>
<sc n="11"/>
<ps n="石部6畫"/>
<zy>注音：ㄎㄨㄤˋ</zy>
<t>
<ph/>《篇海類編》：古猛切，音礦──金銀璞也。
</t>
<wh n="kby0000" unicode="254C6" wid="010">𥓆</wh>
<sc n="12"/>
<ps n="石部7畫"/>
<zy>注音：ㄌㄧㄣˇ</zy>
<t>
<ph/>《篇海類編》：良忍切，音廩──石貌。
</t>
<wh n="kby0000" unicode="254C7" wid="011">𥓇</wh>
<sc n="12"/>
<ps n="石部7畫"/>
<zy>注音：ㄉㄨˇ</zy>
<t>
<ph/>《龍龕》：都毒切，音篤──矺也。
</t>
<wh n="kby0000" unicode="25528" wid="012">𥔨</wh>
<sc n="14"/>
<ps n="石部9畫"/>
<zy>注音：ㄗㄢˋ</zy>
<t>
<ph/>《篇海類編》：子末切，音拶──逼也。
</t>
<wh n="kby0000" unicode="25529" wid="013">𥔩</wh>
<sc n="14"/>
<ps n="石部9畫"/>
<zy>注音：ㄑㄧˇ</zy>
<t>
<ph/>《龍龕》：康札切──問也。
</t>
<wh n="kby0000" unicode="2552A" wid="014">𥔪</wh>
<sc n="14"/>
<ps n="石部9畫"/>
<zy>注音：ㄔㄣˇ</zy>
<t>
<ph/>《五音篇海》：初錦切──反土也。
</t>
<wh n="kby0000" unicode="2552B" wid="015">𥔫</wh>
<sc n="14"/>
<ps n="石部9畫"/>
<zy>注音：ㄙㄤˇ</zy>
<t>
<ph/>《篇海類編》：音顙──鼓磉石。
</t>
<wh n="kby0000" unicode="25545" wid="016">𥕅</wh>
<sc n="15"/>
<ps n="石部10畫"/>
<zy>注音：ㄑㄩ-</zy>
<t>
<ph/>《篇海類編》：七余切──同砠，石山戴土。
</t>
<wh n="kby0000" unicode="25546" wid="017">𥕆</wh>
<sc n="15"/>
<ps n="石部10畫"/>
<zy>注音：ㄌㄧˋ</zy>
<t>
<ph/>《字彙補》：初錦切，參上聲。黃香〈九宮賦〉：抶礕礰而朴雷公。〔註〕礰，一作𥕆。
</t>
<wh n="kby0000" unicode="25547" wid="018">𥕇</wh>
<sc n="15"/>
<ps n="石部10畫"/>
<zy>注音：ㄉㄚˇ</zy>
<t>
<ph/>《篇海類編》：都瓦切，音打──雌黃也。
</t>
<wh n="kby0000" unicode="25548" wid="019">𥕈</wh>
<sc n="15"/>
<ps n="石部10畫"/>
<zy>注音：ㄔㄢˋ</zy>
<t>
<ph/>《字彙補》：楚扇切，音懺──碾繒石也。
</t>
<wh n="kby0000" unicode="7915" wid="020">礕</wh>
<sc n="18"/>
<ps n="石部13畫"/>
<zy>注音：ㄆㄧ-</zy>
<t>
<ph/>《五音篇海》：普擊切──與礔同。礕礰，石聲也。
</t>
<wh n="kby0000" unicode="2378F" wid="021">𣞏</wh>
<sc n="18"/>
<ps n="石部13畫"/>
<t>
<ph/>《字彙補》：音未詳。《太清金液神氣經》：東嶽姓歲名𣞏。
</t>
<wh n="kby0000" unicode="2154E" wid="022">𡕎</wh>
<sc n="20"/>
<ps n="石部15畫"/>
<t>
<ph/>《字彙補》：與蠹同。《𥡆天子傳》：𡕎書於羽林。
</t>
<wh n="kby0000" unicode="255EA" wid="023">𥗪</wh>
<sc n="22"/>
<ps n="石部17畫"/>
<zy>注音：ㄐㄧㄤ-</zy>
<t>
<ph/>《篇海類編》：音薑──石也。
</t>
<wh n="kby0000" unicode="25603" wid="024">𥘃</wh>
<sc n="29"/>
<ps n="石部24畫"/>
<zy>注音：ㄌㄧㄥˊ</zy>
<t>
<ph/>《五音集韻》：力丁切，音靈──石砱也。
</t>
<part>示部</part>
<wh n="kby0000" unicode="2564B" wid="025">𥙋</wh>
<sc n="9"/>
<ps n="示部5畫"/>
<zy>注音：ㄔㄨㄟˋ</zy>
<t>
<ph/>《篇海類編》：蚩瑞切，吹去聲──祟也。
</t>
<wh n="kby0000" unicode="2AC47" wid="026">&kxr-01652;</wh>
<sc n="16"/>
<ps n="示部6畫"/>
<zy>注音：ㄏㄨㄛˋ</zy>
<t>
<ph/>《川篇》：胡果切──&kxr-01652;惠也。
</t>
<wh n="kby0000" unicode="4111" wid="027">䄑</wh>
<sc n="13"/>
<ps n="示部8畫"/>
<zy>注音：ㄏㄨㄛˊ</zy>
<t>
<ph/>《字彙補》：何沫切，音活──祠也。
</t>
<wh n="kby0000" unicode="256C2" wid="028">𥛂</wh>
<sc n="13"/>
<ps n="示部9畫"/>
<zy>注音：ㄓㄨ-,ㄓㄨˋ</zy>
<t>
<ph/>《篇海類編》：音朱──咒人詛名。又，音注──義同。
</t>
<wh n="kby0000" unicode="22FC6" wid="029">𢿆</wh>
<sc n="13"/>
<ps n="示部9畫"/>
<zy>注音：ㄙㄨㄟˋ</zy>
<t>
<ph/>《篇海類編》：想恚切，音碎。《方言》：楚人問吉凶也。
</t>
<wh n="kby0000" unicode="2059F" wid="030">𠖟</wh>
<sc n="14"/>
<ps n="示部9畫"/>
<zy>注音：ㄧㄣ-</zy>
<t>
<ph/>《五音篇海》：音因──敬也、塞也。
</t>
<wh n="kby0000" unicode="256C3" wid="031">𥛃</wh>
<sc n="13"/>
<ps n="示部9畫"/>
<t>
<ph/>《說文》：神本字。
</t>
<wh n="kby0000" unicode="25711" wid="032">𥜑</wh>
<sc n="17"/>
<ps n="示部13畫"/>
<zy>注音：ㄌㄧㄡˋ</zy>
<t>
<ph/>《龍龕》：力又切，音溜──祀也。
</t>
<wh n="kby0000" unicode="25723" wid="033">𥜣</wh>
<sc n="20"/>
<ps n="示部16畫"/>
<t>
<ph/>《字彙補》：與禱同。《廣雅》：𥜣禜，禳祭也。
</t>
<wh n="kby0000" unicode="2572F" wid="034">𥜯</wh>
<sc n="22"/>
<ps n="示部18畫"/>
<t>
<ph/>《說文長箋》：禫本字。
</t>
<wh n="kby0000" unicode="27186" wid="035">𧆆</wh>
<sc n="25"/>
<ps n="示部21畫"/>
<t>
<ph/>《集韻》：同禴。
</t>
<wh n="kby0000" unicode="4125" wid="036">䄥</wh>
<sc n="29"/>
<ps n="示部24畫"/>
<t>
<ph/>《集韻》：同𥜧。
</t>
<part>禸部</part>
<wh n="kby0000" unicode="6B76" wid="037">歶</wh>
<sc n="15"/>
<ps n="禸部10畫"/>
<t>
<ph/>《字彙補》：音未詳。《荀子．禮論篇》：絲歶縷翣。〔註〕絲歶未詳，蓋亦喪車之飾，或曰歶讀爲魚，謂以銅魚懸於地下，縷讀爲柳，蔞字誤爲縷字耳。
</t>
<wh n="kby0000" unicode="25744" wid="038">𥝄</wh>
<sc n="14"/>
<ps n="禸部10畫"/>
<t>
<ph/>《字彙補》：萬本字。《𡌨雅》：蜂名。
</t>
<wh n="kby0000" unicode="25745" wid="039">𥝅</wh>
<sc n="15"/>
<ps n="禸部11畫"/>
<t>
<ph/>《說文長箋》：與萬同。
</t>
<wh n="kby0000" unicode="2574A" wid="040">𥝊</wh>
<sc n="21"/>
<ps n="禸部17畫"/>
<zy>注音：ㄈㄟˋ</zy>
<t>
<ph/>《龍龕》：扶味切──獸名。又，扶喟切──義同。
</t>
<part>禾部</part>
<wh n="kby0000" unicode="25762" wid="041">𥝢</wh>
<sc n="8"/>
<ps n="禾部3畫"/>
<t>
<ph/>《說文長箋》：同利。
</t>
<wh n="kby0000" unicode="25797" wid="042">𥞗</wh>
<sc n="10"/>
<ps n="禾部5畫"/>
<zy>注音：ㄉㄧㄠˇ</zy>
<t>
<ph/>《龍龕》：都了切──禾穗垂貌。
</t>
<wh n="kby0000" unicode="79EE" wid="043">秮</wh>
<sc n="10"/>
<ps n="禾部5畫"/>
<t>
<ph/>《字彙補》：音未詳。《呂氏春秋》：秮米而不香。
</t>
<wh n="kby0000" unicode="257AF" wid="044">𥞯</wh>
<sc n="11"/>
<ps n="禾部6畫"/>
<zy>注音：ㄗㄨˊ</zy>
<t>
<ph/>《龍龕》：則骨切──䄶𥞯也。
</t>
<wh n="kby0000" unicode="414A" wid="045">䅊</wh>
<sc n="11"/>
<ps n="禾部6畫"/>
<zy>注音：ㄔㄨㄥˊ</zy>
<t>
<ph/>《五音篇海》：直宗切──䅊張，開屋也。
</t>
<wh n="kby0000" unicode="2579D" wid="046">𥞝</wh>
<sc n="11"/>
<ps n="禾部6畫"/>
<t>
<ph/>《篇海類編》：籀文椶字。
</t>
<wh n="kby0000" unicode="257B0" wid="047">𥞰</wh>
<sc n="11"/>
<ps n="禾部6畫"/>
<t>
<ph/>《字彙補》：音未詳。《奇姓《通》：游𥞰，複姓也。《英賢傳》：游𥞰子著書，言法家之事。
</t>
<wh n="kby0000" unicode="257CB" wid="048">𥟋</wh>
<sc n="12"/>
<ps n="禾部7畫"/>
<t>
<ph/>《龍龕》：隨凾云，合是稱字。經文名𥟋世界也。
</t>
<wh n="kby0000" unicode="257FA" wid="049">𥟺</wh>
<sc n="13"/>
<ps n="禾部8畫"/>
<zy>注音：ㄉㄨㄛˇ</zy>
<t>
<ph/>《川篇》：音朶。《字彙補》：穗下曰𥟺。
</t>
<wh n="kby0000" unicode="257FB" wid="050">𥟻</wh>
<sc n="13"/>
<ps n="禾部8畫"/>
<zy>注音：ㄧˊ</zy>
<t>
<ph/>《篇海類編》：音移──遷𥟻易轉也。
</t>
<wh n="kby0000" unicode="25859" wid="051">𥡙</wh>
<sc n="15"/>
<ps n="禾部10畫"/>
<t>
<ph/>《字彙補》：音未詳。《漢鐃謌》：向始𥡙，冷將風陽。
</t>
<wh n="kby0000" unicode="2585A" wid="052">𥡚</wh>
<sc n="15"/>
<ps n="禾部10畫"/>
<t>
<ph/>《字彙補》：與黎同。〈漢孔宙𥓓〉𥡚儀𠙋康儀，卽倪也。
</t>
<wh n="kby0000" unicode="25887" wid="053">𥢇</wh>
<sc n="16"/>
<ps n="禾部11畫"/>
<zy>注音：ㄐㄧㄢˇ</zy>
<t>
<ph/>《篇海類編》：古典切，聲同减──小束也。
</t>
<wh n="kby0000" unicode="2585B" wid="054">𥡛</wh>
<sc n="15"/>
<ps n="禾部10畫"/>
<t>
<ph/>《字彙補》：古鹿切，音谷。出《禪法要解經》。
</t>
<wh n="kby0000" unicode="25888" wid="055">𥢈</wh>
<sc n="16"/>
<ps n="禾部11畫"/>
<zy>注音：ㄒㄩㄢ-</zy>
<t>
<ph/>《字彙補》：市元切，音宣──邊豆也。
</t>
<wh n="kby0000" unicode="417D" wid="056">䅽</wh>
<sc n="16"/>
<ps n="禾部11畫"/>
<zy>注音：ㄒㄧㄣ-</zy>
<t>
<ph/>《字彙補》：讀與馨同。《金匱要略》：䅽飪之邪。
</t>
<wh n="kby0000" unicode="258AD" wid="057">𥢭</wh>
<sc n="17"/>
<ps n="禾部11畫"/>
<zy>注音：ㄅㄧㄝˊ</zy>
<t>
<ph/>《字彙補》：蒲結切，音別──禾香也。
</t>
<wh n="kby0000" unicode="258AE" wid="058">𥢮</wh>
<sc n="17"/>
<ps n="禾部12畫"/>
<t>
<ph/>《字彙補》：秦本字。見羅泌國名記。
</t>
<wh n="kby0000" unicode="258AF" wid="059">𥢯</wh>
<sc n="17"/>
<ps n="禾部12畫"/>
<t>
<ph/>《字彙補》：音未詳。《三尊譜錄》：太上眞皇法字𥢯。
</t>
<wh n="kby0000" unicode="258B0" wid="060">𥢰</wh>
<sc n="17"/>
<ps n="禾部12畫"/>
<zy>注音：ㄔㄨㄟˋ,ㄉㄨㄛ-</zy>
<t>
<ph/>《字彙補》：垂毀切，音菙。《廣雅》：𥢰，積也。又，丁禾切，音多。
</t>
<wh n="kby0000" unicode="258D3" wid="061">𥣓</wh>
<sc n="18"/>
<ps n="禾部13畫"/>
<zy>注音：ㄗ-</zy>
<t>
<ph/>《篇海類編》：子之切，音兹──禾生貌。
</t>
<wh n="kby0000" unicode="258E8" wid="062">𥣨</wh>
<sc n="20"/>
<ps n="禾部13畫"/>
<t>
<ph/>《字彙補》：同秋。見漢楊著𥓓。
</t>
<part>立部</part>
<pb id="1492"/>
<wh n="kby0000" unicode="25ACD" wid="001">𥫍</wh>
<sc n="20"/>
<ps n="立部15畫"/>
<t>
<ph/>《五音篇海》：籀文童字。
</t>
</xml>